asynqp_consumer/__init__.py
asynqp_consumer/connect.py
asynqp_consumer/consumer.py
asynqp_consumer/helpers.py
asynqp_consumer/message.py
asynqp_consumer/queue.py
asynqp_consumer/records.py
asynqp_consumer-0.4.0.dist-info/LICENCE
asynqp_consumer-0.4.0.dist-info/METADATA
asynqp_consumer-0.4.0.dist-info/WHEEL
asynqp_consumer-0.4.0.dist-info/top_level.txt
asynqp_consumer-0.4.0.dist-info/RECORD
