Metadata-Version: 2.1
Name: asynqp-consumer
Version: 0.4.0
Summary: Consumer utility class for AMQP
Home-page: https://github.com/tkukushkin/asynqp-consumer
Author: Timofey Kukushkin
Author-email: tima@kukushkin.me
License: UNKNOWN
Platform: UNKNOWN
Classifier: Development Status :: 3 - Alpha
Classifier: Programming Language :: Python :: 3.6
Classifier: License :: OSI Approved :: MIT License
Classifier: Intended Audience :: Developers
Classifier: Intended Audience :: Information Technology
Classifier: Intended Audience :: Telecommunications Industry
Classifier: Natural Language :: English
Classifier: Operating System :: OS Independent
Classifier: Topic :: Software Development
Classifier: Topic :: Software Development :: Libraries
Classifier: Topic :: Software Development :: Libraries :: Python Modules
Classifier: Topic :: System :: Networking
Requires-Dist: asynqp (>=0.5.1)
Provides-Extra: test
Requires-Dist: pycodestyle ; extra == 'test'
Requires-Dist: pylint ; extra == 'test'
Requires-Dist: pytest (==4.5.0) ; extra == 'test'
Requires-Dist: pytest-asyncio (==0.10.0) ; extra == 'test'
Requires-Dist: pytest-cov (==2.7.1) ; extra == 'test'
Requires-Dist: pytest-mock (==1.10.4) ; extra == 'test'
